.gitignore
.travis.yml
LICENSE
README.md
requirements-test.txt
requirements.txt
setup.py
chafic/__init__.py
chafic/cli.py
chafic/storage.py
chafic.egg-info/PKG-INFO
chafic.egg-info/SOURCES.txt
chafic.egg-info/dependency_links.txt
chafic.egg-info/entry_points.txt
chafic.egg-info/requires.txt
chafic.egg-info/top_level.txt
tests/__init__.py
tests/test_storage.py