Metadata-Version: 2.1
Name: chafic
Version: 0.1.5
Summary: chakki Financial Report Corpus
Home-page: https://github.com/chakki-works/chaFiC
Author: icoxfog417
Author-email: icoxfog417@yahoo.co.jp
License: MIT
Platform: UNKNOWN
